distinction/__init__.py
distinction/classifier.py
distinction-0.0.1.7.dist-info/METADATA
distinction-0.0.1.7.dist-info/WHEEL
distinction-0.0.1.7.dist-info/licenses/LICENSE
distinction-0.0.1.7.dist-info/RECORD
