Metadata-Version: 2.4
Name: distinction
Version: 0.0.1.7
Summary: A fast binary classifier built on semantic search.
Project-URL: Homepage, https://github.com/er1kb/distinction
Project-URL: Bug Tracker, https://github.com/er1kb/distinction/issues
Author-email: Erik Broman <mikroberna@gmail.com>
License-Expression: MIT
License-File: LICENSE
Keywords: binary classification,cosine similarity,embeddings,feature selection,sentence transformer
Classifier: Development Status :: 3 - Alpha
Classifier: Intended Audience :: Other Audience
Classifier: License :: OSI Approved :: MIT License
Classifier: Natural Language :: English
Classifier: Natural Language :: Swedish
Classifier: Operating System :: OS Independent
Classifier: Programming Language :: Python :: 3 :: Only
Requires-Python: >=3.9
Requires-Dist: numpy>=1.25.0
Requires-Dist: sentence-transformers>=3.0.1
Provides-Extra: plot
Requires-Dist: plotext>=5.3.2; extra == 'plot'
